dirconf.py
pongo/__init__.py
pongo/config.py
pongo/connect.py
pongo/indentedtext.py
pongo/main.py
pongo/run.py
pongo/targets.py
pongo/scripts/pongo-lineinfile
pongo/scripts/rinstall
pongo/scripts/rsub
pongo_cm-0.1.1.dist-info/LICENSE.rsub
pongo_cm-0.1.1.dist-info/METADATA
pongo_cm-0.1.1.dist-info/WHEEL
pongo_cm-0.1.1.dist-info/entry_points.txt
pongo_cm-0.1.1.dist-info/top_level.txt
pongo_cm-0.1.1.dist-info/RECORD
