Metadata-Version: 2.1
Name: pongo-cm
Version: 0.1.1
Summary: Server configuration managment tool
License: Apache
License-File: LICENSE.rsub
Requires-Dist: jinja2
